LICENSE.md
MANIFEST.in
README.md
setup.cfg
setup.py
version.py
pus/__init__.py
pus/_folder.py
pus/_pus.py
pus/_testit.py
pus.egg-info/PKG-INFO
pus.egg-info/SOURCES.txt
pus.egg-info/dependency_links.txt
pus.egg-info/entry_points.txt
pus.egg-info/requires.txt
pus.egg-info/top_level.txt
pus.egg-info/zip-safe
pus/test/__init__.py
pus/test/setup.cfg
pus/test/test_pus.py