Metadata-Version: 2.1
Name: pus
Version: 0.0.1
Summary: Update the required packages in setup.cfg file
Home-page: https://github.com/limix/pus
Author: Danilo Horta
Author-email: horta@ebi.ac.uk
Maintainer: Danilo Horta
Maintainer-email: horta@ebi.ac.uk
License: MIT
Download-URL: https://github.com/limix/pus
Keywords: function,optimisation
Platform: Windows
Platform: MacOS
Platform: Linux
Classifier: Development Status :: 5 - Production/Stable
Classifier: License :: OSI Approved :: MIT License
Classifier: Operating System :: OS Independent
Classifier: Programming Language :: Python
